slutterprime/__init__.py
slutterprime/eatme.py
slutterprime-1.0.0.dist-info/licenses/LICENSE
slutterprime-1.0.0.dist-info/WHEEL
slutterprime-1.0.0.dist-info/METADATA
slutterprime-1.0.0.dist-info/RECORD
