Metadata-Version: 2.4
Name: slutterprime
Version: 1.0.0
Summary: A funny execute module, enjoy.
Author-email: Next <Lever@smartconnection.api>
License-Expression: GPL-3.0-or-later
License-File: LICENSE
